{"css":"","framework":"duck-10.0.0","title":"עזרה עבור פנקס הגופנים","build_id":"5748a2fe094622073d14da53","icon":"..\/SharedGlobalArt\/AppIconDefault_FontBook.png","sections":{},"birdseed_version":5,"toc":["fntbcc65037b","fntbk1000","fntbk1003","fb34860","fntbk1001","fntb2bcb512d","fntbk1014"],"locale":"he","version":"10.12","enable_tracking":false,"source_schema":"apd-schema","platform":"mac","build_date":"2016.05.27-12:49:41","landing":"fntbede246a6","product":"fontbook","urls":{},"copyright":"","show_previous_next":false,"topics":{"fb34860":{"name":"יצירת אוספים וספריות"},"fb34862":{"name":"שחזור גופנים סטנדרטיים"},"fntbk1004":{"name":"העדפות פנקס הגופנים"},"fntbk1000":{"name":"התקנה והצגה של גופנים"},"fntbede246a6":{"name":"עזרה עבור פנקס הגופנים","href":"fntbede246a6.html","categories":["landing"]},"fntbcc65037b":{"name":"מבט כולל על פנקס הגופנים"},"fntbk1003":{"name":"וידוא תקינות גופנים","searchName":"אימות תקינות של גופנים ב״פנקס הגופנים״"},"fntbk1001":{"name":"הדפסת גופנים","searchName":"הדפסת גופנים ב״פנקס הגופנים״"},"fntb2bcb512d":{"name":"הסרה או ביטול של גופנים"},"fntbk1014":{"name":"ייצוא גופנים","searchName":"ייצוא של גופנים מ״פנקס הגופנים״"}},"copyright_text":"Copyright © 2016 Apple בע״מ. כל הזכויות שמורות."}